assets/script.py
assets/eyeball/eyeball_check.py
demo/calibration_widget.py
demo/constants.py
demo/gaze_dot_canvas.py
demo/main.py
scripts/ml_routines/data.py
scripts/ml_routines/eval_autoencoder.py
scripts/ml_routines/eval_eye_of_the_typer.py
scripts/ml_routines/eval_eye_of_the_typer_3d.py
scripts/ml_routines/eval_maml.py
scripts/ml_routines/tfjs_convert.py
scripts/ml_routines/train_autoencoder.py
scripts/ml_routines/train_maml.py
scripts/ml_routines/utils.py
scripts/preprocessing/eyediap.py
scripts/preprocessing/gazecapture.py
scripts/preprocessing/mpiifacegaze.py
scripts/preprocessing/output_space.py
scripts/preprocessing/preprocess.py
scripts/preprocessing/utils.py
scripts/tests/screen_projection_example.py
scripts/tests/space_transformation_test.py
scripts/tests/test.py
scripts/tests/test_data_normalization.py
scripts/tests/test_vis.py
webeyetrack/__init__.py
webeyetrack/__logger.py
webeyetrack/aug.py
webeyetrack/blazegaze.py
webeyetrack/constants.py
webeyetrack/data_protocols.py
webeyetrack/filter.py
webeyetrack/kalman_filter.py
webeyetrack/model_based.py
webeyetrack/open3d_utilities.py
webeyetrack/tf_utils.py
webeyetrack/utilities.py
webeyetrack/vis.py
webeyetrack/webeyetrack.py
webeyetrack/webeyetrack3D.py
webeyetrack-0.0.1.dist-info/METADATA
webeyetrack-0.0.1.dist-info/WHEEL
webeyetrack-0.0.1.dist-info/top_level.txt
webeyetrack-0.0.1.dist-info/RECORD
