Metadata-Version: 2.4
Name: webeyetrack
Version: 0.0.1
Summary: WebEyeTrack: Robust & Scalable Gaze Tracking for Web Applications
Author-email: Eduardo Davalos <eduardo.davalos.anaya@vanderbilt.edu>
License-Expression: MIT
Project-URL: homepath, https://redforestai.github.io/WebEyeTrack/
Project-URL: repository, https://github.com/RedForestAI/WebEyeTrack
Keywords: eye-tracking,scalable,rgb,gaze
Classifier: Programming Language :: Python :: 3
Requires-Python: >3.6
Requires-Dist: mediapipe
Requires-Dist: numpy
Requires-Dist: opencv-python
Requires-Dist: scipy
Provides-Extra: threed
Requires-Dist: trimesh; extra == "threed"
Requires-Dist: open3d; extra == "threed"
